Metadata-Version: 2.1
Name: hanan-qc
Version: 0.0.1
Summary: Basic quantum circuit package
Home-page: 
Author: Abdul Hanan
Author-email: abdulhanan22170@gmail.com
License: MIT
Keywords: Quantumcircuit
Classifier: Development Status :: 5 - Production/Stable
Classifier: Intended Audience :: Education
Classifier: Operating System :: Microsoft :: Windows :: Windows 10
Classifier: License :: OSI Approved :: MIT License
Classifier: Programming Language :: Python :: 3
License-File: LICENCE.txt
